apsw/__init__.cpython-314t-i386-linux-musl.so
apsw/__init__.pyi
apsw/__main__.py
apsw/_unicode.cpython-314t-i386-linux-musl.so
apsw/bestpractice.py
apsw/ext.py
apsw/fts5.py
apsw/fts5aux.py
apsw/fts5query.py
apsw/fts_test_strings
apsw/py.typed
apsw/shell.py
apsw/speedtest.py
apsw/trace.py
apsw/unicode.py
apsw/tests/__main__.py
apsw/tests/carray.py
apsw/tests/ftstests.py
apsw/tests/jsonb.py
apsw/tests/sessiontests.py
apsw-3.51.2.0.dist-info/METADATA
apsw-3.51.2.0.dist-info/WHEEL
apsw-3.51.2.0.dist-info/entry_points.txt
apsw-3.51.2.0.dist-info/top_level.txt
apsw-3.51.2.0.dist-info/RECORD
apsw-3.51.2.0.dist-info/licenses/LICENSE
