Metadata-Version: 2.4
Name: apsw
Version: 3.51.2.0
Summary: Another Python SQLite Wrapper
Home-page: https://github.com/rogerbinns/apsw
Author: Roger Binns
Author-email: rogerb@rogerbinns.com
License: any-OSI
Project-URL: Changelog, https://rogerbinns.github.io/apsw/changes.html
Project-URL: Documentation, https://rogerbinns.github.io/apsw/
Project-URL: Issue Tracker, https://github.com/rogerbinns/apsw/issues
Project-URL: Code, https://github.com/rogerbinns/apsw
Project-URL: Example, https://rogerbinns.github.io/apsw/example.html
Keywords: database,sqlite
Platform: any
Classifier: Development Status :: 5 - Production/Stable
Classifier: Intended Audience :: Developers
Classifier: Programming Language :: C
Classifier: Programming Language :: Python :: 3
Classifier: Topic :: Database :: Front-Ends
Requires-Python: >=3.10
License-File: LICENSE
Dynamic: author
Dynamic: author-email
Dynamic: classifier
Dynamic: description
Dynamic: description-content-type
Dynamic: home-page
Dynamic: keywords
Dynamic: license
Dynamic: license-file
Dynamic: platform
Dynamic: project-url
Dynamic: requires-python
Dynamic: summary
